[{"Program Name":"Precious Metal Products","Item":"17XA","Item Description":"2017 AM LIBERTY 24K GOLD 1 OZ","Adj. Net Demand":"31771","Date Sales Report is Valid":"5/10/2020"},{"Program Name":"Annual Sets","Item":"18AC","Item Description":"2018 ATB QTR CIRC SET","Adj. Net Demand":"22415","Date Sales Report is Valid":"5/10/2020"},{"Program Name":"Special Collectibles","Item":"18AE","Item Description":"2018 ATB QTR 3-COIN SET - APOSTLE ISL","Adj. Net Demand":"14654","Date Sales Report is Valid":"5/10/2020"},{"Program Name":"Special Collectibles","Item":"18AF","Item Description":"2018 ATB QTR 3-COIN SET - VOYAGEURS","Adj. Net Demand":"14591","Date Sales Report is Valid":"5/10/2020"},{"Program Name":"Special Collectibles","Item":"18AG","Item Description":"2018 ATB QTR 3-COIN SET - CMBRLND ISL","Adj. Net Demand":"13697","Date Sales Report is Valid":"5/10/2020"},{"Program Name":"Special Collectibles","Item":"18AH","Item Description":"2018 ATB QTR 3-COIN SET - BLOCK ISL","Adj. Net Demand":"13609","Date Sales Report is Valid":"5/10/2020"},{"Program Name":"Precious Metal Products","Item":"18EJ","Item Description":"2018 AM EAGLE PLATINUM PROOF 1 OZ","Adj. Net Demand":"14041","Date Sales Report is Valid":"5/10/2020"},{"Program Name":"Annual Sets","Item":"18GA","Item Description":"2018 AI $1 PROOF COIN","Adj. Net Demand":"211361","Date Sales Report is Valid":"5/10/2020"},{"Program Name":"Rolls &amp; Bags &amp; Boxes","Item":"18GRA","Item Description":"2018 AI $1 25-COIN ROLL (P)","Adj. Net Demand":"17070","Date Sales Report is Valid":"5/10/2020"},{"Program Name":"Rolls &amp; Bags &amp; Boxes","Item":"18GRE","Item Description":"2018 AI $1 25-COIN ROLL (D)","Adj. Net Demand":"16086","Date Sales Report is Valid":"5/10/2020"},{"Program Name":"Special Collectibles","Item":"18RD","Item Description":"2018 BIRTH SET","Adj. Net Demand":"32262","Date Sales Report is Valid":"5/10/2020"},{"Program Name":"Precious Metal Products","Item":"18XF","Item Description":"2018 AM LIBERTY 24K GOLD 1/10 OZ","Adj. Net Demand":"32805","Date Sales Report is Valid":"5/10/2020"},{"Program Name":"Annual Sets","Item":"19AA","Item Description":"2019 ATB QTR UNC SET","Adj. Net Demand":"27831","Date Sales Report is Valid":"5/10/2020"},{"Program Name":"Rolls &amp; Bags &amp; Boxes","Item":"19ABF","Item Description":"2019 ATB QTR 100-COIN BAG - AM MEM PARK (S)","Adj. Net Demand":"4090","Date Sales Report is Valid":"5/10/2020"},{"Program Name":"Rolls &amp; Bags &amp; Boxes","Item":"19ABG","Item Description":"2019 ATB QTR 100-COIN BAG - WAR IN THE PACIFIC (P)","Adj. Net Demand":"2331","Date Sales Report is Valid":"5/10/2020"},{"Program Name":"Rolls &amp; Bags &amp; Boxes","Item":"19ABH","Item Description":"2019 ATB QTR 100-COIN BAG - WAR IN THE PACIFIC (D)","Adj. Net Demand":"2238","Date Sales Report is Valid":"5/10/2020"},{"Program Name":"Rolls &amp; Bags &amp; Boxes","Item":"19ABJ","Item Description":"2019 ATB QTR 100-COIN BAG - WAR IN THE PACIFIC (S)","Adj. Net Demand":"4104","Date Sales Report is Valid":"5/10/2020"},{"Program Name":"Rolls &amp; Bags &amp; Boxes","Item":"19ABK","Item Description":"2019 ATB QTR 100-COIN BAG - SAN ANTONIO MSN (P)","Adj. Net Demand":"2297","Date Sales Report is Valid":"5/10/2020"},{"Program Name":"Rolls &amp; Bags &amp; Boxes","Item":"19ABL","Item Description":"2019 ATB QTR 100-COIN BAG - SAN ANTONIO MSN (D)","Adj. Net Demand":"2215","Date Sales Report is Valid":"5/10/2020"},{"Program Name":"Rolls &amp; Bags &amp; Boxes","Item":"19ABM","Item Description":"2019 ATB QTR 100-COIN BAG - SAN ANTONIO MSN (S)","Adj. Net Demand":"4019","Date Sales Report is Valid":"5/10/2020"},{"Program Name":"Rolls &amp; Bags &amp; Boxes","Item":"19ABN","Item Description":"2019 ATB QTR 100-COIN BAG - FC RVR OF NO RTN (P)","Adj. Net Demand":"2106","Date Sales Report is Valid":"5/10/2020"},{"Program Name":"Rolls &amp; Bags &amp; Boxes","Item":"19ABP","Item Description":"2019 ATB QTR 100-COIN BAG - FC RVR OF NO RTN (D)","Adj. Net Demand":"2039","Date Sales Report is Valid":"5/10/2020"},{"Program Name":"Rolls &amp; Bags &amp; Boxes","Item":"19ABQ","Item Description":"2019 ATB QTR 100-COIN BAG - FC RVR OF NO RTN (S)","Adj. Net Demand":"3746","Date Sales Report is Valid":"5/10/2020"},{"Program Name":"Annual Sets","Item":"19AC","Item Description":"2019 ATB QTR CIRC SET","Adj. Net Demand":"20461","Date Sales Report is Valid":"5/10/2020"},{"Program Name":"Special Collectibles","Item":"19AD","Item Description":"2019 ATB QTR 3-COIN SET - LOWELL NTL PARK","Adj. Net Demand":"14467","Date Sales Report is Valid":"5/10/2020"},{"Program Name":"Special Collectibles","Item":"19AE","Item Description":"2019 ATB QTR 3-COIN SET - AM MEM PARK","Adj. Net Demand":"14320","Date Sales Report is Valid":"5/10/2020"},{"Program Name":"Special Collectibles","Item":"19AF","Item Description":"2019 ATB QTR 3-COIN SET - WAR IN THE PACIFIC","Adj. Net Demand":"14954","Date Sales Report is Valid":"5/10/2020"},{"Program Name":"Special Collectibles","Item":"19AG","Item Description":"2019 ATB QTR 3-COIN SET - SAN ANTONIO MSN","Adj. Net Demand":"14626","Date Sales Report is Valid":"5/10/2020"},{"Program Name":"Special Collectibles","Item":"19AH","Item Description":"2019 ATB QTR 3-COIN SET - FC RVR OF NO RTN","Adj. Net Demand":"12692","Date Sales Report is Valid":"5/10/2020"},{"Program Name":"Precious Metal Products","Item":"19AJ","Item Description":"2019 ATB SILVER UNC 5 OZ - LOWELL NTL PARK","Adj. Net Demand":"15189","Date Sales Report is Valid":"5/10/2020"},{"Program Name":"Precious Metal Products","Item":"19AK","Item Description":"2019 ATB SILVER UNC 5 OZ - AM MEM PARK","Adj. Net Demand":"14447","Date Sales Report is Valid":"5/10/2020"},{"Program Name":"Precious Metal Products","Item":"19AL","Item Description":"2019 ATB SILVER UNC 5 OZ - WAR IN THE PACIFIC","Adj. Net Demand":"15503","Date Sales Report is Valid":"5/10/2020"},{"Program Name":"Precious Metal Products","Item":"19AM","Item Description":"2019 ATB SILVER UNC 5 OZ - SAN ANTONIO MSN","Adj. Net Demand":"14699","Date Sales Report is Valid":"5/10/2020"},{"Program Name":"Precious Metal Products","Item":"19AN","Item Description":"2019 ATB SILVER UNC 5 OZ - FC RVR OF NO RTN","Adj. Net Demand":"13683","Date Sales Report is Valid":"5/10/2020"},{"Program Name":"Annual Sets","Item":"19AP","Item Description":"2019 ATB QTR PROOF SET","Adj. Net Demand":"72330","Date Sales Report is Valid":"5/10/2020"},{"Program Name":"Annual Sets","Item":"19AQ","Item Description":"2019 ATB QTR SILVER PROOF SET","Adj. Net Demand":"73175","Date Sales Report is Valid":"5/10/2020"},{"Program Name":"Rolls &amp; Bags &amp; Boxes","Item":"19ARD","Item Description":"2019 ATB QTR 2-ROLL SET - AM MEM PARK (P&amp;D)","Adj. Net Demand":"6056","Date Sales Report is Valid":"5/10/2020"},{"Program Name":"Rolls &amp; Bags &amp; Boxes","Item":"19ARE","Item Description":"2019 ATB QTR 40-COIN ROLL - AM MEM PARK (S)","Adj. Net Demand":"3858","Date Sales Report is Valid":"5/10/2020"},{"Program Name":"Rolls &amp; Bags &amp; Boxes","Item":"19ARF","Item Description":"2019 ATB QTR 3-ROLL SET - AM MEM PARK (P&amp;D&amp;S)","Adj. Net Demand":"8468","Date Sales Report is Valid":"5/10/2020"},{"Program Name":"Rolls &amp; Bags &amp; Boxes","Item":"19ARG","Item Description":"2019 ATB QTR 2-ROLL SET - WAR IN THE PACIFIC (P&amp;D)","Adj. Net Demand":"5997","Date Sales Report is Valid":"5/10/2020"},{"Program Name":"Rolls &amp; Bags &amp; Boxes","Item":"19ARH","Item Description":"2019 ATB QTR 40-COIN ROLL - WAR IN THE PACIFIC (S)","Adj. Net Demand":"3738","Date Sales Report is Valid":"5/10/2020"},{"Program Name":"Rolls &amp; Bags &amp; Boxes","Item":"19ARJ","Item Description":"2019 ATB QTR 3-ROLL SET - WAR IN THE PACIFIC (P&amp;D&amp;S)","Adj. Net Demand":"8631","Date Sales Report is Valid":"5/10/2020"},{"Program Name":"Rolls &amp; Bags &amp; Boxes","Item":"19ARK","Item Description":"2019 ATB QTR 2-ROLL SET - SAN ANTONIO MSN (P&amp;D)","Adj. Net Demand":"5929","Date Sales Report is Valid":"5/10/2020"},{"Program Name":"Rolls &amp; Bags &amp; Boxes","Item":"19ARL","Item Description":"2019 ATB QTR 40-COIN ROLL - SAN ANTONIO MSN (S)","Adj. Net Demand":"3688","Date Sales Report is Valid":"5/10/2020"},{"Program Name":"Rolls &amp; Bags &amp; Boxes","Item":"19ARM","Item Description":"2019 ATB QTR 3-ROLL SET - SAN ANTONIO MSN (P&amp;D&amp;S)","Adj. Net Demand":"8671","Date Sales Report is Valid":"5/10/2020"},{"Program Name":"Rolls &amp; Bags &amp; Boxes","Item":"19ARN","Item Description":"2019 ATB QTR 2-ROLL SET - FC RVR OF NO RTN (P&amp;D)","Adj. Net Demand":"5655","Date Sales Report is Valid":"5/10/2020"},{"Program Name":"Rolls &amp; Bags &amp; Boxes","Item":"19ARP","Item Description":"2019 ATB QTR 40-COIN ROLL - FC RVR OF NO RTN (S)","Adj. Net Demand":"3533","Date Sales Report is Valid":"5/10/2020"},{"Program Name":"Rolls &amp; Bags &amp; Boxes","Item":"19ARQ","Item Description":"2019 ATB QTR 3-ROLL SET - FC RVR OF NO RTN (P&amp;D&amp;S)","Adj. Net Demand":"8090","Date Sales Report is Valid":"5/10/2020"},{"Program Name":"Precious Metal Products","Item":"19DA","Item Description":"2019 AM LIBERTY 24K GOLD 1 OZ","Adj. Net Demand":"9277","Date Sales Report is Valid":"5/10/2020"},{"Program Name":"Precious Metal Products","Item":"19DB","Item Description":"2019 AM LIBERTY SILVER MEDAL 2.5 OZ","Adj. Net Demand":"34546","Date Sales Report is Valid":"5/10/2020"},{"Program Name":"Precious Metal Products","Item":"19EB","Item Description":"2019 AM EAGLE GOLD PROOF 1 OZ","Adj. Net Demand":"5629","Date Sales Report is Valid":"5/10/2020"},{"Program Name":"Precious Metal Products","Item":"19EF","Item Description":"2019 AM EAGLE GOLD PROOF 4-COIN SET","Adj. Net Demand":"7476","Date Sales Report is Valid":"5/10/2020"},{"Program Name":"Precious Metal Products","Item":"19EG","Item Description":"2019 AM EAGLE SILVER UNC 1 OZ","Adj. Net Demand":"134151","Date Sales Report is Valid":"5/10/2020"},{"Program Name":"Precious Metal Products","Item":"19EJ","Item Description":"2019 AM EAGLE PLATINUM PROOF 1 OZ","Adj. Net Demand":"10301","Date Sales Report is Valid":"5/10/2020"},{"Program Name":"Precious Metal Products","Item":"19EK","Item Description":"2019 AM EAGLE PALLADIUM PROOF 1 OZ","Adj. Net Demand":"17318","Date Sales Report is Valid":"5/10/2020"},{"Program Name":"Precious Metal Products","Item":"19EL","Item Description":"2019 AM BUFFALO GOLD PROOF 1 OZ","Adj. Net Demand":"14834","Date Sales Report is Valid":"5/10/2020"},{"Program Name":"Precious Metal Products","Item":"19EM","Item Description":"2019 AM EAGLE SILVER PROOF 1 OZ (S)","Adj. Net Demand":"146730","Date Sales Report is Valid":"5/10/2020"},{"Program Name":"Annual Sets","Item":"19GA","Item Description":"2019 AI $1 PROOF SET","Adj. Net Demand":"95717","Date Sales Report is Valid":"5/10/2020"},{"Program Name":"Rolls &amp; Bags &amp; Boxes","Item":"19GBA","Item Description":"2019 AI $1 100-COIN BAG - DE (P)","Adj. Net Demand":"2083","Date Sales Report is Valid":"5/10/2020"},{"Program Name":"Rolls &amp; Bags &amp; Boxes","Item":"19GBB","Item Description":"2019 AI $1 100-COIN BAG - PA (P)","Adj. Net Demand":"1951","Date Sales Report is Valid":"5/10/2020"},{"Program Name":"Rolls &amp; Bags &amp; Boxes","Item":"19GBC","Item Description":"2019 AI $1 100-COIN BAG - NJ (P)","Adj. Net Demand":"2293","Date Sales Report is Valid":"5/10/2020"},{"Program Name":"Rolls &amp; Bags &amp; Boxes","Item":"19GBD","Item Description":"2019 AI $1 100-COIN BAG - GA (P)","Adj. Net Demand":"2007","Date Sales Report is Valid":"5/10/2020"},{"Program Name":"Rolls &amp; Bags &amp; Boxes","Item":"19GBE","Item Description":"2019 AI $1 100-COIN BAG - DE (D)","Adj. Net Demand":"2276","Date Sales Report is Valid":"5/10/2020"},{"Program Name":"Rolls &amp; Bags &amp; Boxes","Item":"19GBF","Item Description":"2019 AI $1 100-COIN BAG - PA (D)","Adj. Net Demand":"1949","Date Sales Report is Valid":"5/10/2020"},{"Program Name":"Rolls &amp; Bags &amp; Boxes","Item":"19GBG","Item Description":"2019 AI $1 100-COIN BAG - NJ (D)","Adj. Net Demand":"2102","Date Sales Report is Valid":"5/10/2020"},{"Program Name":"Rolls &amp; Bags &amp; Boxes","Item":"19GBH","Item Description":"2019 AI $1 100-COIN BAG - GA (D)","Adj. Net Demand":"1896","Date Sales Report is Valid":"5/10/2020"},{"Program Name":"Special Collectibles","Item":"19GE","Item Description":"2019 AI $1 REV PRF - DE","Adj. Net Demand":"57252","Date Sales Report is Valid":"5/10/2020"},{"Program Name":"Special Collectibles","Item":"19GF","Item Description":"2019 AI $1 REV PRF - PA","Adj. Net Demand":"40666","Date Sales Report is Valid":"5/10/2020"},{"Program Name":"Special Collectibles","Item":"19GG","Item Description":"2019 AI $1 REV PRF - NJ","Adj. Net Demand":"35033","Date Sales Report is Valid":"5/10/2020"},{"Program Name":"Special Collectibles","Item":"19GH","Item Description":"2019 AI $1 REV PRF - GA","Adj. Net Demand":"30460","Date Sales Report is Valid":"5/10/2020"},{"Program Name":"Rolls &amp; Bags &amp; Boxes","Item":"19GRA","Item Description":"2019 AI $1 25-COIN ROLL - DE (P)","Adj. Net Demand":"6579","Date Sales Report is Valid":"5/10/2020"},{"Program Name":"Rolls &amp; Bags &amp; Boxes","Item":"19GRB","Item Description":"2019 AI $1 25-COIN ROLL - PA (P)","Adj. Net Demand":"6514","Date Sales Report is Valid":"5/10/2020"},{"Program Name":"Rolls &amp; Bags &amp; Boxes","Item":"19GRC","Item Description":"2019 AI $1 25-COIN ROLL - NJ (P)","Adj. Net Demand":"5931","Date Sales Report is Valid":"5/10/2020"},{"Program Name":"Rolls &amp; Bags &amp; Boxes","Item":"19GRD","Item Description":"2019 AI $1 25-COIN ROLL - GA (P)","Adj. Net Demand":"5451","Date Sales Report is Valid":"5/10/2020"},{"Program Name":"Rolls &amp; Bags &amp; Boxes","Item":"19GRE","Item Description":"2019 AI $1 25-COIN ROLL - DE (D)","Adj. Net Demand":"6238","Date Sales Report is Valid":"5/10/2020"},{"Program Name":"Rolls &amp; Bags &amp; Boxes","Item":"19GRF","Item Description":"2019 AI $1 25-COIN ROLL - PA (D)","Adj. Net Demand":"5900","Date Sales Report is Valid":"5/10/2020"},{"Program Name":"Rolls &amp; Bags &amp; Boxes","Item":"19GRG","Item Description":"2019 AI $1 25-COIN ROLL - NJ (D)","Adj. Net Demand":"5575","Date Sales Report is Valid":"5/10/2020"},{"Program Name":"Rolls &amp; Bags &amp; Boxes","Item":"19GRH","Item Description":"2019 AI $1 25-COIN ROLL - GA (D)","Adj. Net Demand":"5238","Date Sales Report is Valid":"5/10/2020"},{"Program Name":"Rolls &amp; Bags &amp; Boxes","Item":"19KA","Item Description":"2019 HALF-DOLLAR 200-COIN BAG (P&amp;D)","Adj. Net Demand":"8636","Date Sales Report is Valid":"5/10/2020"},{"Program Name":"Rolls &amp; Bags &amp; Boxes","Item":"19KB","Item Description":"2019 HALF-DOLLAR 2-ROLL SET (P&amp;D)","Adj. Net Demand":"21406","Date Sales Report is Valid":"5/10/2020"},{"Program Name":"Rolls &amp; Bags &amp; Boxes","Item":"19NA","Item Description":"2019  NA $1 25-COIN ROLL (P)","Adj. Net Demand":"15683","Date Sales Report is Valid":"5/10/2020"},{"Program Name":"Rolls &amp; Bags &amp; Boxes","Item":"19NB","Item Description":"2019  NA $1 25-COIN ROLL (D)","Adj. Net Demand":"15082","Date Sales Report is Valid":"5/10/2020"},{"Program Name":"Rolls &amp; Bags &amp; Boxes","Item":"19ND","Item Description":"2019  NA $1 250-COIN BOX (D)","Adj. Net Demand":"1927","Date Sales Report is Valid":"5/10/2020"},{"Program Name":"Rolls &amp; Bags &amp; Boxes","Item":"19NE","Item Description":"2019  NA $1 100-COIN BAG (P)","Adj. Net Demand":"1796","Date Sales Report is Valid":"5/10/2020"},{"Program Name":"Rolls &amp; Bags &amp; Boxes","Item":"19NF","Item Description":"2019  NA $1 100-COIN BAG (D)","Adj. Net Demand":"1580","Date Sales Report is Valid":"5/10/2020"},{"Program Name":"Special Collectibles","Item":"19NR","Item Description":"2019  NA $1 COIN &amp; CURRENCY SET","Adj. Net Demand":"45884","Date Sales Report is Valid":"5/10/2020"},{"Program Name":"Special Collectibles","Item":"19RD","Item Description":"2019 BIRTH SET","Adj. Net Demand":"28546","Date Sales Report is Valid":"5/10/2020"},{"Program Name":"Special Collectibles","Item":"19RE","Item Description":"2019 HAPPY BIRTHDAY SET","Adj. Net Demand":"18103","Date Sales Report is Valid":"5/10/2020"},{"Program Name":"Special Collectibles","Item":"19RF","Item Description":"2019 CONGRATULATIONS SET","Adj. Net Demand":"27522","Date Sales Report is Valid":"5/10/2020"},{"Program Name":"Annual Sets","Item":"19RG","Item Description":"2019 PROOF SET","Adj. Net Demand":"575711","Date Sales Report is Valid":"5/10/2020"},{"Program Name":"Annual Sets","Item":"19RH","Item Description":"2019 SILVER PROOF SET","Adj. Net Demand":"397377","Date Sales Report is Valid":"5/10/2020"},{"Program Name":"Annual Sets","Item":"19RJ","Item Description":"2019 UNC SET","Adj. Net Demand":"327299","Date Sales Report is Valid":"5/10/2020"},{"Program Name":"Special Collectibles","Item":"19RX","Item Description":"2019 YOUTH COIN &amp; CURRENCY SET","Adj. Net Demand":"9190","Date Sales Report is Valid":"5/10/2020"},{"Program Name":"Special Collectibles","Item":"19XC","Item Description":"2019 MIGHTY MINTERS ORNAMENT","Adj. Net Demand":"4362","Date Sales Report is Valid":"5/10/2020"},{"Program Name":"Special Collectibles","Item":"19XD","Item Description":"2019 UNITED STATES MINT ORNAMENT","Adj. Net Demand":"7684","Date Sales Report is Valid":"5/10/2020"},{"Program Name":"Special Collectibles","Item":"19XGB","Item Description":"2019 EXPLORE AND DISCOVER SET","Adj. Net Demand":"33125","Date Sales Report is Valid":"5/10/2020"},{"Program Name":"Annual Sets","Item":"20AA","Item Description":"2020 ATB QTR UNC SET","Adj. Net Demand":"20974","Date Sales Report is Valid":"5/10/2020"},{"Program Name":"Rolls &amp; Bags &amp; Boxes","Item":"20ABA","Item Description":"2020 ATB QTR 100-COIN BAG - AMERICAN SAMOA (P)","Adj. Net Demand":"2378","Date Sales Report is Valid":"5/10/2020"},{"Program Name":"Rolls &amp; Bags &amp; Boxes","Item":"20ABB","Item Description":"2020 ATB QTR 100-COIN BAG - AMERICAN SAMOA (D)","Adj. Net Demand":"2193","Date Sales Report is Valid":"5/10/2020"},{"Program Name":"Rolls &amp; Bags &amp; Boxes","Item":"20ABC","Item Description":"2020 ATB QTR 100-COIN BAG - AMERICAN SAMOA (S)","Adj. Net Demand":"4235","Date Sales Report is Valid":"5/10/2020"},{"Program Name":"Special Collectibles","Item":"20AD","Item Description":"2020 ATB QTR 3-COIN SET - AMERICAN SAMOA","Adj. Net Demand":"12661","Date Sales Report is Valid":"5/10/2020"},{"Program Name":"Precious Metal Products","Item":"20AJ","Item Description":"2020 ATB SILVER UNC 5 OZ - AMERICAN SAMOA","Adj. Net Demand":"14485","Date Sales Report is Valid":"5/10/2020"},{"Program Name":"Annual Sets","Item":"20AP","Item Description":"2020 ATB QTR PROOF SET","Adj. Net Demand":"48608","Date Sales Report is Valid":"5/10/2020"},{"Program Name":"Annual Sets","Item":"20AQ","Item Description":"2020 ATB QTR SILVER PROOF SET","Adj. Net Demand":"50988","Date Sales Report is Valid":"5/10/2020"},{"Program Name":"Rolls &amp; Bags &amp; Boxes","Item":"20ARA","Item Description":"2020 ATB QTR 2-ROLL SET - AMERICAN SAMOA (P&amp;D)","Adj. Net Demand":"5582","Date Sales Report is Valid":"5/10/2020"},{"Program Name":"Rolls &amp; Bags &amp; Boxes","Item":"20ARB","Item Description":"2020 ATB QTR 40-COIN ROLL - AMERICAN SAMOA (S)","Adj. Net Demand":"3975","Date Sales Report is Valid":"5/10/2020"},{"Program Name":"Rolls &amp; Bags &amp; Boxes","Item":"20ARC","Item Description":"2020 ATB QTR 3-ROLL SET - AMERICAN SAMOA (P&amp;D&amp;S)","Adj. Net Demand":"8433","Date Sales Report is Valid":"5/10/2020"},{"Program Name":"Precious Metal Products","Item":"20EA","Item Description":"2020 AM EAGLE SILVER PROOF 1 OZ (W)","Adj. Net Demand":"272916","Date Sales Report is Valid":"5/10/2020"},{"Program Name":"Precious Metal Products","Item":"20EA040","Item Description":"2020 AM EAGLE SILVER PROOF 1 OZ (W)  40 COIN","Adj. Net Demand":"594","Date Sales Report is Valid":"5/10/2020"},{"Program Name":"Precious Metal Products","Item":"20EB","Item Description":"2020 AM EAGLE GOLD PROOF 1 OZ","Adj. Net Demand":"2677","Date Sales Report is Valid":"5/10/2020"},{"Program Name":"Precious Metal Products","Item":"20EC","Item Description":"2020 AM EAGLE GOLD PROOF 1/2 OZ.","Adj. Net Demand":"1001","Date Sales Report is Valid":"5/10/2020"},{"Program Name":"Precious Metal Products","Item":"20ED","Item Description":"2020 AM EAGLE GOLD PROOF 1/4 OZ.","Adj. Net Demand":"1579","Date Sales Report is Valid":"5/10/2020"},{"Program Name":"Precious Metal Products","Item":"20EE","Item Description":"2020 AM EAGLE GOLD PROOF 1/10 OZ.","Adj. Net Demand":"5336","Date Sales Report is Valid":"5/10/2020"},{"Program Name":"Precious Metal Products","Item":"20EF","Item Description":"2020 AM EAGLE GOLD PROOF 4-COIN SET","Adj. Net Demand":"5406","Date Sales Report is Valid":"5/10/2020"},{"Program Name":"Precious Metal Products","Item":"20EJ","Item Description":"2020 AM EAGLE PLATINUM PROOF 1 OZ","Adj. Net Demand":"6390","Date Sales Report is Valid":"5/10/2020"},{"Program Name":"Precious Metal Products","Item":"20EL","Item Description":"2020 AM BUFFALO GOLD PROOF 1 OZ","Adj. Net Demand":"7094","Date Sales Report is Valid":"5/10/2020"},{"Program Name":"Rolls &amp; Bags &amp; Boxes","Item":"20NA","Item Description":"2020  NA $1 25-COIN ROLL (P)","Adj. Net Demand":"10638","Date Sales Report is Valid":"5/10/2020"},{"Program Name":"Rolls &amp; Bags &amp; Boxes","Item":"20NB","Item Description":"2020  NA $1 25-COIN ROLL (D)","Adj. Net Demand":"10455","Date Sales Report is Valid":"5/10/2020"},{"Program Name":"Rolls &amp; Bags &amp; Boxes","Item":"20NC","Item Description":"2020  NA $1 250-COIN BOX (P)","Adj. Net Demand":"875","Date Sales Report is Valid":"5/10/2020"},{"Program Name":"Rolls &amp; Bags &amp; Boxes","Item":"20ND","Item Description":"2020  NA $1 250-COIN BOX (D)","Adj. Net Demand":"951","Date Sales Report is Valid":"5/10/2020"},{"Program Name":"Rolls &amp; Bags &amp; Boxes","Item":"20NE","Item Description":"2020  NA $1 100-COIN BAG (P)","Adj. Net Demand":"1518","Date Sales Report is Valid":"5/10/2020"},{"Program Name":"Rolls &amp; Bags &amp; Boxes","Item":"20NF","Item Description":"2020  NA $1 100-COIN BAG (D)","Adj. Net Demand":"1632","Date Sales Report is Valid":"5/10/2020"},{"Program Name":"Special Collectibles","Item":"20RD","Item Description":"2020 BIRTH SET","Adj. Net Demand":"10708","Date Sales Report is Valid":"5/10/2020"},{"Program Name":"Special Collectibles","Item":"20RE","Item Description":"2020 HAPPY BIRTHDAY SET","Adj. Net Demand":"10351","Date Sales Report is Valid":"5/10/2020"},{"Program Name":"Special Collectibles","Item":"20RF","Item Description":"2020 CONGRATULATIONS SET","Adj. Net Demand":"24398","Date Sales Report is Valid":"5/10/2020"},{"Program Name":"Annual Sets","Item":"20RG","Item Description":"2020 PROOF SET (+ W1 NICKEL)","Adj. Net Demand":"249806","Date Sales Report is Valid":"5/10/2020"},{"Program Name":"Annual Sets","Item":"20RH","Item Description":"2020 SILVER PROOF SET (+ W2 NICKEL)","Adj. Net Demand":"190886","Date Sales Report is Valid":"5/10/2020"},{"Program Name":"Precious Metal Products","Item":"S801","Item Description":"GEORGE WASHINGTON PRESIDENTIAL SILVER MEDAL","Adj. Net Demand":"24265","Date Sales Report is Valid":"5/10/2020"},{"Program Name":"Precious Metal Products","Item":"S802","Item Description":"JOHN ADAMS PRESIDENTIAL SILVER MEDAL","Adj. Net Demand":"18673","Date Sales Report is Valid":"5/10/2020"},{"Program Name":"Precious Metal Products","Item":"S803","Item Description":"THOMAS JEFFERSON PRESIDENTIAL SILVER MEDAL","Adj. Net Demand":"16076","Date Sales Report is Valid":"5/10/2020"},{"Program Name":"Precious Metal Products","Item":"S804","Item Description":"JAMES MADISON SILVER PRESIDENTIAL MEDAL","Adj. Net Demand":"12221","Date Sales Report is Valid":"5/10/2020"},{"Program Name":"Precious Metal Products","Item":"S805","Item Description":"JAMES MONROE SILVER PRESIDENTIAL MEDAL","Adj. Net Demand":"11385","Date Sales Report is Valid":"5/10/2020"},{"Program Name":"Precious Metal Products","Item":"S806","Item Description":"JOHN QUINCY ADAMS PRESIDENTIAL SILVER MEDAL","Adj. Net Demand":"10835","Date Sales Report is Valid":"5/10/2020"},{"Program Name":"Precious Metal Products","Item":"S807","Item Description":"ANDREW JACKSON PRESIDENTIAL SILVER MEDAL","Adj. Net Demand":"10303","Date Sales Report is Valid":"5/10/2020"}]