[{"Program":"Special Collectibles","Program Item":"N71","Product":"2010 ATB QTR 3-COIN SET - HOT SPRINGS","Sales to Date":"22Ω712","Sales Reporting Date":"03/20/2016"},{"Program":"Special Collectibles","Program Item":"N72","Product":"2010 ATB QTR 3-COIN SET - YELLOWSTONE","Sales to Date":"24Ω107","Sales Reporting Date":"03/20/2016"},{"Program":"Special Collectibles","Program Item":"N73","Product":"2010 ATB QTR 3 COIN SET - YOSEMITE","Sales to Date":"21Ω365","Sales Reporting Date":"03/20/2016"},{"Program":"Special Collectibles","Program Item":"N74","Product":"2010 ATB QTR 3-COIN SET - GRAND CANYON","Sales to Date":"21Ω281","Sales Reporting Date":"03/20/2016"},{"Program":"Special Collectibles","Program Item":"N75","Product":"2010 ATB QTR 3-COIN SET - MT HOOD","Sales to Date":"17Ω904","Sales Reporting Date":"03/20/2016"},{"Program":"Annual Sets","Program Item":"N86","Product":"2010 ATB QTR UNC SET","Sales to Date":"40Ω918","Sales Reporting Date":"03/20/2016"},{"Program":"Annual Sets","Program Item":"N89","Product":"2010 ATB QTR CIRC SET","Sales to Date":"38Ω580","Sales Reporting Date":"03/20/2016"},{"Program":"Special Collectibles","Program Item":"P33","Product":"2010 PRES $1 COIN COVER - FILLMORE","Sales to Date":"23Ω696","Sales Reporting Date":"03/20/2016"},{"Program":"Special Collectibles","Program Item":"P34","Product":"2010 PRES $1 COIN COVER - PIERCE","Sales to Date":"22Ω151","Sales Reporting Date":"03/20/2016"},{"Program":"Special Collectibles","Program Item":"P35","Product":"2010 PRES $1 COIN COVER - BUCHANAN","Sales to Date":"20Ω881","Sales Reporting Date":"03/20/2016"},{"Program":"Special Collectibles","Program Item":"XN4","Product":"2010 PRES $1 & FS MDL SET - FILMORE","Sales to Date":"10Ω986","Sales Reporting Date":"03/20/2016"},{"Program":"Special Collectibles","Program Item":"XO4","Product":"2010 PRES $1 & FS MDL SET - PIERCE","Sales to Date":"8Ω772","Sales Reporting Date":"03/20/2016"},{"Program":"Special Collectibles","Program Item":"XP4","Product":"2010 PRES $1 & FS MDL SET - BUCHANAN","Sales to Date":"8Ω779","Sales Reporting Date":"03/20/2016"},{"Program":"Special Collectibles","Program Item":"N76","Product":"2011 ATB QTR 3-COIN SET - GETTYSBURG","Sales to Date":"22Ω042","Sales Reporting Date":"03/20/2016"},{"Program":"Special Collectibles","Program Item":"N77","Product":"2011 ATB QTR 3-COIN SET - GLACIER","Sales to Date":"18Ω369","Sales Reporting Date":"03/20/2016"},{"Program":"Special Collectibles","Program Item":"N78","Product":"2011 ATB QTR 3-COIN SET - OLYMPIC","Sales to Date":"17Ω181","Sales Reporting Date":"03/20/2016"},{"Program":"Special Collectibles","Program Item":"N79","Product":"2011 ATB QTR 3-COIN SET - VICKSBURG","Sales to Date":"17Ω574","Sales Reporting Date":"03/20/2016"},{"Program":"Special Collectibles","Program Item":"N80","Product":"2011 ATB QTR 3-COIN SET - CHICKASAW","Sales to Date":"15Ω753","Sales Reporting Date":"03/20/2016"},{"Program":"Annual Sets","Program Item":"N91","Product":"2011 ATB QTR CIRC SET","Sales to Date":"35Ω086","Sales Reporting Date":"03/20/2016"},{"Program":"Annual Sets","Program Item":"N93","Product":"2011 ATB QTR UNC SET","Sales to Date":"39Ω648","Sales Reporting Date":"03/20/2016"},{"Program":"Special Collectibles","Program Item":"P37","Product":"2011 PRES $1 COIN COVER - JOHNSON","Sales to Date":"19Ω338","Sales Reporting Date":"03/20/2016"},{"Program":"Special Collectibles","Program Item":"P38","Product":"2011 PRES $1 COIN COVER - GRANT","Sales to Date":"20Ω016","Sales Reporting Date":"03/20/2016"},{"Program":"Special Collectibles","Program Item":"P39","Product":"2011 PRES $1 COIN COVER - HAYES","Sales to Date":"17Ω551","Sales Reporting Date":"03/20/2016"},{"Program":"Special Collectibles","Program Item":"P40","Product":"2011 PRES $1 COIN COVER - GARFIELD","Sales to Date":"16Ω784","Sales Reporting Date":"03/20/2016"},{"Program":"Annual Sets","Program Item":"XE5","Product":"2011 PRES $1 UNC SET","Sales to Date":"84Ω651","Sales Reporting Date":"03/20/2016"},{"Program":"Special Collectibles","Program Item":"XN5","Product":"2011 PRES $1 & FS MDL SET - JOHNSON","Sales to Date":"7Ω109","Sales Reporting Date":"03/20/2016"},{"Program":"Special Collectibles","Program Item":"XO5","Product":"2011 PRES $1 & FS MDL SET - GRANT","Sales to Date":"7Ω806","Sales Reporting Date":"03/20/2016"},{"Program":"Special Collectibles","Program Item":"XP5","Product":"2011 PRES $1 & FS MDL SET - HAYES","Sales to Date":"6Ω150","Sales Reporting Date":"03/20/2016"},{"Program":"Special Collectibles","Program Item":"XQ5","Product":"2011 PRES $1 & FS MDL SET - GARFIELD","Sales to Date":"5Ω917","Sales Reporting Date":"03/20/2016"},{"Program":"Special Collectibles","Program Item":"N82","Product":"2012 ATB QTR 3-COIN SET - CHACO CULTURE","Sales to Date":"19Ω077","Sales Reporting Date":"03/20/2016"},{"Program":"Special Collectibles","Program Item":"N83","Product":"2012 ATB QTR 3-COIN SET - ACADIA","Sales to Date":"19Ω657","Sales Reporting Date":"03/20/2016"},{"Program":"Special Collectibles","Program Item":"N84","Product":"2012 ATB QTR 3-COIN SET - HAWAII","Sales to Date":"19Ω947","Sales Reporting Date":"03/20/2016"},{"Program":"Special Collectibles","Program Item":"N85","Product":"2012 ATB QTR 3-COIN SET - DENALI","Sales to Date":"17Ω218","Sales Reporting Date":"03/20/2016"},{"Program":"Special Collectibles","Program Item":"P41","Product":"2012 PRES $1 COIN COVER - ARTHUR","Sales to Date":"16Ω907","Sales Reporting Date":"03/20/2016"},{"Program":"Special Collectibles","Program Item":"P42","Product":"2012 PRES $1 COIN COVER - CVLD 1ST","Sales to Date":"15Ω414","Sales Reporting Date":"03/20/2016"},{"Program":"Special Collectibles","Program Item":"P43","Product":"2012 PRES $1 COIN COVER - HARRISON","Sales to Date":"14Ω978","Sales Reporting Date":"03/20/2016"},{"Program":"Special Collectibles","Program Item":"P44","Product":"2012 PRES $1 COIN COVER - CVLD 2ND","Sales to Date":"14Ω247","Sales Reporting Date":"03/20/2016"},{"Program":"Annual Sets","Program Item":"XE6","Product":"2012 PRES $1 UNC SET","Sales to Date":"99Ω743","Sales Reporting Date":"03/20/2016"},{"Program":"Special Collectibles","Program Item":"XN6","Product":"2012 PRES $1 & FS MDL SET - ARTHUR","Sales to Date":"5Ω786","Sales Reporting Date":"03/20/2016"},{"Program":"Special Collectibles","Program Item":"XO6","Product":"2012 PRES $1 & FS MDL SET - CVLD 1ST","Sales to Date":"5Ω245","Sales Reporting Date":"03/20/2016"},{"Program":"Special Collectibles","Program Item":"XP6","Product":"2012 PRES $1 & FS MDL SET - HARRISON","Sales to Date":"5Ω161","Sales Reporting Date":"03/20/2016"},{"Program":"Special Collectibles","Program Item":"XQ6","Product":"2012 PRES $1 & FS MDL SET - CVLD 2ND","Sales to Date":"4Ω998","Sales Reporting Date":"03/20/2016"},{"Program":"Special Collectibles","Program Item":"N15","Product":"2013 BIRTH SET","Sales to Date":"41Ω178","Sales Reporting Date":"03/20/2016"},{"Program":"Special Collectibles","Program Item":"N16","Product":"2013 HAPPY BIRTHDAY SET","Sales to Date":"11Ω509","Sales Reporting Date":"03/20/2016"},{"Program":"Special Collectibles","Program Item":"N46","Product":"2013 ATB QTR 3-COIN SET - WH MTN","Sales to Date":"18Ω056","Sales Reporting Date":"03/20/2016"},{"Program":"Special Collectibles","Program Item":"N47","Product":"2013 ATB QTR 3-COIN SET - PY VTY","Sales to Date":"17Ω126","Sales Reporting Date":"03/20/2016"},{"Program":"Special Collectibles","Program Item":"N48","Product":"2013 ATB QTR 3-COIN SET - GT BSN","Sales to Date":"15Ω006","Sales Reporting Date":"03/20/2016"},{"Program":"Special Collectibles","Program Item":"N49","Product":"2013 ATB QTR 3-COIN SET - MCHNRY","Sales to Date":"15Ω634","Sales Reporting Date":"03/20/2016"},{"Program":"Special Collectibles","Program Item":"N50","Product":"2013 ATB QTR 3-COIN SET - MT RSM","Sales to Date":"16Ω792","Sales Reporting Date":"03/20/2016"},{"Program":"Annual Sets","Program Item":"N96","Product":"2013 ATB QTR UNC SET","Sales to Date":"41Ω759","Sales Reporting Date":"03/20/2016"},{"Program":"Annual Sets","Program Item":"N97","Product":"2013 ATB QTR CIRC SET","Sales to Date":"27Ω801","Sales Reporting Date":"03/20/2016"},{"Program":"Special Collectibles","Program Item":"P45","Product":"2013 PRES $1 COIN COVER - MCKINLEY","Sales to Date":"14Ω517","Sales Reporting Date":"03/20/2016"},{"Program":"Special Collectibles","Program Item":"P46","Product":"2013 PRES $1 COIN COVER - ROOSEVLT","Sales to Date":"16Ω771","Sales Reporting Date":"03/20/2016"},{"Program":"Special Collectibles","Program Item":"P47","Product":"2013 PRES $1 COIN COVER - TAFT","Sales to Date":"13Ω406","Sales Reporting Date":"03/20/2016"},{"Program":"Special Collectibles","Program Item":"P48","Product":"2013 PRES $1 COIN COVER - WILSON","Sales to Date":"13Ω021","Sales Reporting Date":"03/20/2016"},{"Program":"Special Collectibles","Program Item":"TR9","Product":"2013 ROOSEVLT YOUTH SET","Sales to Date":"9Ω916","Sales Reporting Date":"03/20/2016"},{"Program":"Rolls & Bags & Boxes","Program Item":"AW1","Product":"2014 ATB QTR 100-COIN BAG - ARCHES (P)","Sales to Date":"2Ω528","Sales Reporting Date":"03/20/2016"},{"Program":"Rolls & Bags & Boxes","Program Item":"AW2","Product":"2014 ATB QTR 100-COIN BAG - ARCHES (D)","Sales to Date":"2Ω513","Sales Reporting Date":"03/20/2016"},{"Program":"Rolls & Bags & Boxes","Program Item":"AW3","Product":"2014 ATB QTR 100-COIN BAG - ARCHES (S)","Sales to Date":"5Ω863","Sales Reporting Date":"03/20/2016"},{"Program":"Rolls & Bags & Boxes","Program Item":"AW4","Product":"2014 ATB QTR 2-ROLL SET - ARCHES (P&D)","Sales to Date":"8Ω877","Sales Reporting Date":"03/20/2016"},{"Program":"Rolls & Bags & Boxes","Program Item":"AW5","Product":"2014 ATB QTR 40-COIN ROLL - ARCHES (S)","Sales to Date":"5Ω682","Sales Reporting Date":"03/20/2016"},{"Program":"Rolls & Bags & Boxes","Program Item":"AW6","Product":"2014 ATB QTR 3-ROLL SET - ARCHES (P&D&S)","Sales to Date":"10Ω520","Sales Reporting Date":"03/20/2016"},{"Program":"Annual Sets","Program Item":"DE8","Product":"2014 PRES $1 CIRC SET (P)","Sales to Date":"12Ω442","Sales Reporting Date":"03/20/2016"},{"Program":"Annual Sets","Program Item":"DE9","Product":"2014 PRES $1 CIRC SET (D)","Sales to Date":"9Ω181","Sales Reporting Date":"03/20/2016"},{"Program":"Rolls & Bags & Boxes","Program Item":"FR1","Product":"2014 PRES $1 25-COIN ROLL - ROOSEVLT (P)","Sales to Date":"55Ω834","Sales Reporting Date":"03/20/2016"},{"Program":"Rolls & Bags & Boxes","Program Item":"FR2","Product":"2014 PRES $1 25-COIN ROLL - ROOSEVLT (D)","Sales to Date":"51Ω150","Sales Reporting Date":"03/20/2016"},{"Program":"Rolls & Bags & Boxes","Program Item":"GD1","Product":"2014 ATB QTR 100-COIN BAG - GT SND (P)","Sales to Date":"2Ω571","Sales Reporting Date":"03/20/2016"},{"Program":"Rolls & Bags & Boxes","Program Item":"GD2","Product":"2014 ATB QTR 100-COIN BAG - GT SND (D)","Sales to Date":"2Ω481","Sales Reporting Date":"03/20/2016"},{"Program":"Rolls & Bags & Boxes","Program Item":"GD3","Product":"2014 ATB QTR 100-COIN BAG - GT SND (S)","Sales to Date":"5Ω540","Sales Reporting Date":"03/20/2016"},{"Program":"Rolls & Bags & Boxes","Program Item":"GD4","Product":"2014 ATB QTR 2-ROLL SET - GT SND (P&D)","Sales to Date":"8Ω509","Sales Reporting Date":"03/20/2016"},{"Program":"Rolls & Bags & Boxes","Program Item":"GD5","Product":"2014 ATB QTR 40-COIN ROLL - GT SND (S)","Sales to Date":"5Ω351","Sales Reporting Date":"03/20/2016"},{"Program":"Rolls & Bags & Boxes","Program Item":"GD6","Product":"2014 ATB QTR 3-ROLL SET - GT SND (P&D&S)","Sales to Date":"10Ω193","Sales Reporting Date":"03/20/2016"},{"Program":"Special Collectibles","Program Item":"HB1","Product":"2014 HAPPY BIRTHDAY SET","Sales to Date":"12Ω926","Sales Reporting Date":"03/20/2016"},{"Program":"Rolls & Bags & Boxes","Program Item":"HH1","Product":"2014 PRES $1 25-COIN ROLL - HOOVER (P)","Sales to Date":"51Ω919","Sales Reporting Date":"03/20/2016"},{"Program":"Rolls & Bags & Boxes","Program Item":"HH2","Product":"2014 PRES $1 25-COIN ROLL - HOOVER (D)","Sales to Date":"45Ω069","Sales Reporting Date":"03/20/2016"},{"Program":"First Spouse","Program Item":"HP2","Product":"2014 FS GOLD UNC 1/2 OZ - HARDING","Sales to Date":"1Ω871","Sales Reporting Date":"03/20/2016"},{"Program":"First Spouse","Program Item":"HP4","Product":"2014 FS GOLD UNC 1/2 OZ - COOLIDGE","Sales to Date":"1Ω892","Sales Reporting Date":"03/20/2016"},{"Program":"First Spouse","Program Item":"HP5","Product":"2014 FS GOLD PROOF 1/2 OZ - HOOVER","Sales to Date":"2Ω370","Sales Reporting Date":"03/20/2016"},{"Program":"First Spouse","Program Item":"HP6","Product":"2014 FS GOLD UNC 1/2 OZ - HOOVER","Sales to Date":"1Ω849","Sales Reporting Date":"03/20/2016"},{"Program":"Annual Sets","Program Item":"N98","Product":"2014 ATB QTR UNC SET","Sales to Date":"28Ω654","Sales Reporting Date":"03/20/2016"},{"Program":"Special Collectibles","Program Item":"P49","Product":"2014 PRES $1 COIN COVER - HARDING","Sales to Date":"12Ω860","Sales Reporting Date":"03/20/2016"},{"Program":"Special Collectibles","Program Item":"P50","Product":"2014 PRES $1 COIN COVER - COOLIDGE","Sales to Date":"12Ω685","Sales Reporting Date":"03/20/2016"},{"Program":"Special Collectibles","Program Item":"P51","Product":"2014 PRES $1 COIN COVER - HOOVER","Sales to Date":"12Ω158","Sales Reporting Date":"03/20/2016"},{"Program":"Special Collectibles","Program Item":"P52","Product":"2014 PRES $1 COIN COVER - ROOSEVLT","Sales to Date":"14Ω513","Sales Reporting Date":"03/20/2016"},{"Program":"Special Collectibles","Program Item":"P88","Product":"2014 ATB QTR 3-COIN SET - SHDOAH","Sales to Date":"16Ω695","Sales Reporting Date":"03/20/2016"},{"Program":"Special Collectibles","Program Item":"P89","Product":"2014 ATB QTR 3-COIN SET - ARCHES","Sales to Date":"15Ω064","Sales Reporting Date":"03/20/2016"},{"Program":"Special Collectibles","Program Item":"P90","Product":"2014 ATB QTR 3-COIN SET - GT SND","Sales to Date":"13Ω509","Sales Reporting Date":"03/20/2016"},{"Program":"Rolls & Bags & Boxes","Program Item":"SH1","Product":"2014 ATB QTR 100-COIN BAG - SHDOAH (P)","Sales to Date":"2Ω722","Sales Reporting Date":"03/20/2016"},{"Program":"Rolls & Bags & Boxes","Program Item":"SH2","Product":"2014 ATB QTR 100-COIN BAG - SHDOAH (D)","Sales to Date":"2Ω667","Sales Reporting Date":"03/20/2016"},{"Program":"Rolls & Bags & Boxes","Program Item":"SH3","Product":"2014 ATB QTR 100-COIN BAG - SHDOAH (S)","Sales to Date":"5Ω804","Sales Reporting Date":"03/20/2016"},{"Program":"Rolls & Bags & Boxes","Program Item":"SH4","Product":"2014 ATB QTR 2-ROLL SET - SHDOAH (P&D)","Sales to Date":"9Ω371","Sales Reporting Date":"03/20/2016"},{"Program":"Rolls & Bags & Boxes","Program Item":"SH5","Product":"2014 ATB QTR 40-COIN ROLL - SHDOAH (S)","Sales to Date":"6Ω183","Sales Reporting Date":"03/20/2016"},{"Program":"Rolls & Bags & Boxes","Program Item":"SH6","Product":"2014 ATB QTR 3-ROLL SET - SHDOAH (P&D&S)","Sales to Date":"10Ω955","Sales Reporting Date":"03/20/2016"},{"Program":"Special Collectibles","Program Item":"UB7","Product":"2014 BIRTH SET","Sales to Date":"33Ω929","Sales Reporting Date":"03/20/2016"},{"Program":"Annual Sets","Program Item":"XE8","Product":"2014 PRES $1 UNC SET","Sales to Date":"60Ω898","Sales Reporting Date":"03/20/2016"},{"Program":"Special Collectibles","Program Item":"K13","Product":"2014 KENNEDY ANNIVERSARY SILVER SET","Sales to Date":"221Ω132","Sales Reporting Date":"03/20/2016"},{"Program":"Rolls & Bags & Boxes","Program Item":"EV1","Product":"2014 ATB QTR 100-COIN BAG - EVRGLD (P)","Sales to Date":"2Ω714","Sales Reporting Date":"03/20/2016"},{"Program":"Rolls & Bags & Boxes","Program Item":"EV2","Product":"2014 ATB QTR 100-COIN BAG - EVRGLD (D)","Sales to Date":"2Ω647","Sales Reporting Date":"03/20/2016"},{"Program":"Rolls & Bags & Boxes","Program Item":"EV3","Product":"2014 ATB QTR 100-COIN BAG - EVRGLD (S)","Sales to Date":"5Ω667","Sales Reporting Date":"03/20/2016"},{"Program":"Rolls & Bags & Boxes","Program Item":"EV4","Product":"2014 ATB QTR 2-ROLL SET - EVRGLD (P&D)","Sales to Date":"8Ω198","Sales Reporting Date":"03/20/2016"},{"Program":"Rolls & Bags & Boxes","Program Item":"EV5","Product":"2014 ATB QTR 40-COIN ROLL - EVRGLD (S)","Sales to Date":"5Ω330","Sales Reporting Date":"03/20/2016"},{"Program":"Rolls & Bags & Boxes","Program Item":"EV6","Product":"2014 ATB QTR 3-ROLL SET - EVRGLD (P&D&S)","Sales to Date":"9Ω993","Sales Reporting Date":"03/20/2016"},{"Program":"Annual Sets","Program Item":"N99","Product":"2014 ATB QTR CIRC SET","Sales to Date":"22Ω081","Sales Reporting Date":"03/20/2016"},{"Program":"Special Collectibles","Program Item":"P91","Product":"2014 ATB QTR 3-COIN SET - EVRGLD","Sales to Date":"13Ω694","Sales Reporting Date":"03/20/2016"},{"Program":"Special Collectibles","Program Item":"YC1","Product":"2014 US MINT COIN DISCOVERY SET","Sales to Date":"7Ω330","Sales Reporting Date":"03/20/2016"},{"Program":"Special Collectibles","Program Item":"N61","Product":"2015 BIRTH SET","Sales to Date":"34Ω544","Sales Reporting Date":"03/20/2016"},{"Program":"Special Collectibles","Program Item":"N62","Product":"2015 HAPPY BIRTHDAY SET","Sales to Date":"14Ω469","Sales Reporting Date":"03/20/2016"},{"Program":"Annual Sets","Program Item":"Q5G","Product":"2015 ATB QTR PROOF SET","Sales to Date":"96Ω450","Sales Reporting Date":"03/20/2016"},{"Program":"Rolls & Bags & Boxes","Program Item":"HT3","Product":"2015 PRES $1 250-COIN BOX - TRUMAN (P)","Sales to Date":"7Ω788","Sales Reporting Date":"03/20/2016"},{"Program":"Rolls & Bags & Boxes","Program Item":"HT4","Product":"2015 PRES $1 250-COIN BOX - TRUMAN (D)","Sales to Date":"5Ω755","Sales Reporting Date":"03/20/2016"},{"Program":"Rolls & Bags & Boxes","Program Item":"HT5","Product":"2015 PRES $1 100-COIN BAG - TRUMAN (P)","Sales to Date":"3Ω477","Sales Reporting Date":"03/20/2016"},{"Program":"Rolls & Bags & Boxes","Program Item":"KN7","Product":"2015 HALF-DOLLAR 200-COIN BAG (P&D)","Sales to Date":"12Ω212","Sales Reporting Date":"03/20/2016"},{"Program":"Rolls & Bags & Boxes","Program Item":"KN8","Product":"2015 HALF-DOLLAR 2-ROLL SET (P&D)","Sales to Date":"25Ω862","Sales Reporting Date":"03/20/2016"},{"Program":"Annual Sets","Program Item":"Q5H","Product":"2015 ATB QTR SILVER PROOF SET","Sales to Date":"98Ω573","Sales Reporting Date":"03/20/2016"},{"Program":"Rolls & Bags & Boxes","Program Item":"HM2","Product":"2015 ATB QTR 100-COIN BAG - HOMSTD (D)","Sales to Date":"2Ω489","Sales Reporting Date":"03/20/2016"},{"Program":"Rolls & Bags & Boxes","Program Item":"HM3","Product":"2015 ATB QTR 100-COIN BAG - HOMSTD (S)","Sales to Date":"5Ω472","Sales Reporting Date":"03/20/2016"},{"Program":"Rolls & Bags & Boxes","Program Item":"HM4","Product":"2015 ATB QTR 2-ROLL SET - HOMSTD (P&D)","Sales to Date":"8Ω522","Sales Reporting Date":"03/20/2016"},{"Program":"Rolls & Bags & Boxes","Program Item":"HM6","Product":"2015 ATB QTR 3-ROLL SET - HOMSTD (P&D&S)","Sales to Date":"10Ω614","Sales Reporting Date":"03/20/2016"},{"Program":"Special Collectibles","Program Item":"NF5","Product":"2015 ATB QTR 3-COIN SET - HOMSTD","Sales to Date":"15Ω261","Sales Reporting Date":"03/20/2016"},{"Program":"Precious Metal Products","Program Item":"SN1","Product":"2015 ATB SILVER UNC 5 OZ - HOMSTD","Sales to Date":"21Ω283","Sales Reporting Date":"03/20/2016"},{"Program":"Annual Sets","Program Item":"PE5","Product":"2015 PRES $1 PROOF SET","Sales to Date":"222Ω066","Sales Reporting Date":"03/20/2016"},{"Program":"Precious Metal Products","Program Item":"PM1","Product":"2015 AM EAGLE GOLD PROOF 1 OZ","Sales to Date":"22Ω734","Sales Reporting Date":"03/20/2016"},{"Program":"Precious Metal Products","Program Item":"PM2","Product":"2015 AM EAGLE GOLD PROOF 1/2 OZ","Sales to Date":"5Ω902","Sales Reporting Date":"03/20/2016"},{"Program":"Precious Metal Products","Program Item":"PM3","Product":"2015 AM EAGLE GOLD PROOF 1/4 OZ","Sales to Date":"5Ω857","Sales Reporting Date":"03/20/2016"},{"Program":"Precious Metal Products","Program Item":"PM4","Product":"2015 AM EAGLE GOLD PROOF 1/10 OZ","Sales to Date":"16Ω851","Sales Reporting Date":"03/20/2016"},{"Program":"Rolls & Bags & Boxes","Program Item":"NT1","Product":"2015 NA $1 25-COIN ROLL (P)","Sales to Date":"16Ω749","Sales Reporting Date":"03/20/2016"},{"Program":"Rolls & Bags & Boxes","Program Item":"NT2","Product":"2015 NA $1 25-COIN ROLL (D)","Sales to Date":"17Ω186","Sales Reporting Date":"03/20/2016"},{"Program":"Rolls & Bags & Boxes","Program Item":"NT3","Product":"2015 NA $1 250-COIN BOX (P)","Sales to Date":"1Ω993","Sales Reporting Date":"03/20/2016"},{"Program":"Rolls & Bags & Boxes","Program Item":"NT4","Product":"2015 NA $1 250-COIN BOX (D)","Sales to Date":"1Ω956","Sales Reporting Date":"03/20/2016"},{"Program":"Rolls & Bags & Boxes","Program Item":"NT5","Product":"2015 NA $1 100-COIN BAG (P)","Sales to Date":"1Ω775","Sales Reporting Date":"03/20/2016"},{"Program":"Rolls & Bags & Boxes","Program Item":"NT6","Product":"2015 NA $1 100-COIN BAG (D)","Sales to Date":"1Ω881","Sales Reporting Date":"03/20/2016"},{"Program":"Annual Sets","Program Item":"P17","Product":"2015 PROOF SET","Sales to Date":"638Ω733","Sales Reporting Date":"03/20/2016"},{"Program":"Precious Metal Products","Program Item":"PM6","Product":"2015 AM BUFFALO GOLD PROOF 1 OZ","Sales to Date":"16Ω592","Sales Reporting Date":"03/20/2016"},{"Program":"Rolls & Bags & Boxes","Program Item":"DW5","Product":"2015 PRES $1 100-COIN BAG - EISENHWR (P)","Sales to Date":"1Ω821","Sales Reporting Date":"03/20/2016"},{"Program":"Rolls & Bags & Boxes","Program Item":"DW6","Product":"2015 PRES $1 100-COIN BAG - EISENHWR (D)","Sales to Date":"1Ω758","Sales Reporting Date":"03/20/2016"},{"Program":"Rolls & Bags & Boxes","Program Item":"DW3","Product":"2015 PRES $1 250-COIN BOX - EISENHWR (P)","Sales to Date":"7Ω468","Sales Reporting Date":"03/20/2016"},{"Program":"Rolls & Bags & Boxes","Program Item":"DW4","Product":"2015 PRES $1 250-COIN BOX - EISENHWR (D)","Sales to Date":"5Ω606","Sales Reporting Date":"03/20/2016"},{"Program":"First Spouse","Program Item":"JQ1","Product":"2015 FS GOLD PROOF 1/2 OZ - TRUMAN","Sales to Date":"2Ω451","Sales Reporting Date":"03/20/2016"},{"Program":"First Spouse","Program Item":"JQ2","Product":"2015 FS GOLD UNC 1/2 OZ - TRUMAN","Sales to Date":"1Ω707","Sales Reporting Date":"03/20/2016"},{"Program":"Rolls & Bags & Boxes","Program Item":"KA6","Product":"2015 ATB QTR 3-ROLL SET - KTCHIE (P&D&S)","Sales to Date":"9Ω794","Sales Reporting Date":"03/20/2016"},{"Program":"Rolls & Bags & Boxes","Program Item":"KA4","Product":"2015 ATB QTR 2-ROLL SET - KTCHIE (P&D)","Sales to Date":"7Ω953","Sales Reporting Date":"03/20/2016"},{"Program":"Rolls & Bags & Boxes","Program Item":"KA5","Product":"2015 ATB QTR 40-COIN ROLL - KTCHIE (S)","Sales to Date":"4Ω787","Sales Reporting Date":"03/20/2016"},{"Program":"Rolls & Bags & Boxes","Program Item":"KA1","Product":"2015 ATB QTR 100-COIN BAG - KTCHIE (P)","Sales to Date":"2Ω377","Sales Reporting Date":"03/20/2016"},{"Program":"Rolls & Bags & Boxes","Program Item":"KA2","Product":"2015 ATB QTR 100-COIN BAG - KTCHIE (D)","Sales to Date":"2Ω341","Sales Reporting Date":"03/20/2016"},{"Program":"Rolls & Bags & Boxes","Program Item":"KA3","Product":"2015 ATB QTR 100-COIN BAG - KTCHIE (S)","Sales to Date":"5Ω136","Sales Reporting Date":"03/20/2016"},{"Program":"Annual Sets","Program Item":"NE2","Product":"2015 ATB QTR UNC SET","Sales to Date":"25Ω189","Sales Reporting Date":"03/20/2016"},{"Program":"Special Collectibles","Program Item":"NF6","Product":"2015 ATB QTR 3-COIN SET - KTCHIE","Sales to Date":"14Ω356","Sales Reporting Date":"03/20/2016"},{"Program":"Annual Sets","Program Item":"U15","Product":"2015 UNC SET","Sales to Date":"301Ω487","Sales Reporting Date":"03/20/2016"},{"Program":"Precious Metal Products","Program Item":"SN2","Product":"2015 ATB SILVER UNC 5 OZ - KTCHIE","Sales to Date":"19Ω449","Sales Reporting Date":"03/20/2016"},{"Program":"Special Collectibles","Program Item":"JP5","Product":"2015 PRES $1 & FS MDL SET - TRUMAN","Sales to Date":"7Ω506","Sales Reporting Date":"03/20/2016"},{"Program":"Precious Metal Products","Program Item":"PM7","Product":"2015 AM EAGLE GOLD UNC 1 OZ","Sales to Date":"6Ω533","Sales Reporting Date":"03/20/2016"},{"Program":"Special Collectibles","Program Item":"P54","Product":"2015 PRES $1 COIN COVER - EISENHWR","Sales to Date":"14Ω672","Sales Reporting Date":"03/20/2016"},{"Program":"First Spouse","Program Item":"JQ3","Product":"2015 FS GOLD PROOF 1/2 OZ - EISENHWR","Sales to Date":"2Ω685","Sales Reporting Date":"03/20/2016"},{"Program":"First Spouse","Program Item":"JQ4","Product":"2015 FS GOLD UNC 1/2 OZ - EISENHWR","Sales to Date":"1Ω776","Sales Reporting Date":"03/20/2016"},{"Program":"Special Collectibles","Program Item":"JP6","Product":"2015 PRES $1 & FS MDL SET - EISENHWR","Sales to Date":"8Ω283","Sales Reporting Date":"03/20/2016"},{"Program":"Annual Sets","Program Item":"SW2","Product":"2015 SILVER PROOF SET","Sales to Date":"366Ω837","Sales Reporting Date":"03/20/2016"},{"Program":"Rolls & Bags & Boxes","Program Item":"KN1","Product":"2015 PRES $1 25-COIN ROLL - KENNEDY (P)","Sales to Date":"49Ω584","Sales Reporting Date":"03/20/2016"},{"Program":"Rolls & Bags & Boxes","Program Item":"KN2","Product":"2015 PRES $1 25-COIN ROLL - KENNEDY (D)","Sales to Date":"44Ω990","Sales Reporting Date":"03/20/2016"},{"Program":"Rolls & Bags & Boxes","Program Item":"KN5","Product":"2015 PRES $1 100-COIN BAG - KENNEDY (P)","Sales to Date":"2Ω144","Sales Reporting Date":"03/20/2016"},{"Program":"Rolls & Bags & Boxes","Program Item":"KN6","Product":"2015 PRES $1 100-COIN BAG - KENNEDY (D)","Sales to Date":"1Ω905","Sales Reporting Date":"03/20/2016"},{"Program":"Rolls & Bags & Boxes","Program Item":"KN3","Product":"2015 PRES $1 250-COIN BOX - KENNEDY (P)","Sales to Date":"7Ω136","Sales Reporting Date":"03/20/2016"},{"Program":"Rolls & Bags & Boxes","Program Item":"KN4","Product":"2015 PRES $1 250-COIN BOX - KENNEDY (D)","Sales to Date":"6Ω504","Sales Reporting Date":"03/20/2016"},{"Program":"First Spouse","Program Item":"JQ5","Product":"2015 FS GOLD PROOF 1/2 OZ - KENNEDY","Sales to Date":"11Ω221","Sales Reporting Date":"03/20/2016"},{"Program":"First Spouse","Program Item":"JQ6","Product":"2015 FS GOLD UNC 1/2 OZ - KENNEDY","Sales to Date":"5Ω930","Sales Reporting Date":"03/20/2016"},{"Program":"Rolls & Bags & Boxes","Program Item":"BD6","Product":"2015 ATB QTR 3-ROLL SET - BL RDG (P&D&S)","Sales to Date":"9Ω872","Sales Reporting Date":"03/20/2016"},{"Program":"Rolls & Bags & Boxes","Program Item":"BD4","Product":"2015 ATB QTR 2-ROLL SET - BL RDG (P&D)","Sales to Date":"7Ω859","Sales Reporting Date":"03/20/2016"},{"Program":"Rolls & Bags & Boxes","Program Item":"BD5","Product":"2015 ATB QTR 40-COIN ROLL - BL RDG (S)","Sales to Date":"4Ω814","Sales Reporting Date":"03/20/2016"},{"Program":"Rolls & Bags & Boxes","Program Item":"BD1","Product":"2015 ATB QTR 100-COIN BAG - BL RDG (P)","Sales to Date":"2Ω308","Sales Reporting Date":"03/20/2016"},{"Program":"Rolls & Bags & Boxes","Program Item":"BD2","Product":"2015 ATB QTR 100-COIN BAG - BL RDG (D)","Sales to Date":"2Ω305","Sales Reporting Date":"03/20/2016"},{"Program":"Rolls & Bags & Boxes","Program Item":"BD3","Product":"2015 ATB QTR 100-COIN BAG - BL RDG (S)","Sales to Date":"4Ω824","Sales Reporting Date":"03/20/2016"},{"Program":"Special Collectibles","Program Item":"NF7","Product":"2015 ATB QTR 3-COIN SET - BL RDG","Sales to Date":"15Ω920","Sales Reporting Date":"03/20/2016"},{"Program":"Special Collectibles","Program Item":"P55","Product":"2015 PRES $1 COIN COVER - KENNEDY","Sales to Date":"21Ω098","Sales Reporting Date":"03/20/2016"},{"Program":"Annual Sets","Program Item":"XE9","Product":"2015 PRES $1 UNC SET","Sales to Date":"53Ω704","Sales Reporting Date":"03/20/2016"},{"Program":"Precious Metal Products","Program Item":"UH8","Product":"UHR 24K GOLD","Sales to Date":"49Ω325","Sales Reporting Date":"03/20/2016"},{"Program":"Rolls & Bags & Boxes","Program Item":"LJ3","Product":"2015 PRES $1 250-COIN BOX - JOHNSON (P)","Sales to Date":"4Ω513","Sales Reporting Date":"03/20/2016"},{"Program":"Rolls & Bags & Boxes","Program Item":"LJ4","Product":"2015 PRES $1 250-COIN BOX - JOHNSON (D)","Sales to Date":"5Ω543","Sales Reporting Date":"03/20/2016"},{"Program":"Rolls & Bags & Boxes","Program Item":"LJ5","Product":"2015 PRES $1 100-COIN BAG - JOHNSON (P)","Sales to Date":"1Ω183","Sales Reporting Date":"03/20/2016"},{"Program":"Rolls & Bags & Boxes","Program Item":"LJ6","Product":"2015 PRES $1 100-COIN BAG - JOHNSON (D)","Sales to Date":"1Ω211","Sales Reporting Date":"03/20/2016"},{"Program":"Special Collectibles","Program Item":"15RA","Product":"2015 COIN & CURRENCY SET","Sales to Date":"86Ω708","Sales Reporting Date":"03/20/2016"},{"Program":"First Spouse","Program Item":"JQ7","Product":"2015 FS GOLD PROOF 1/2 OZ - JOHNSON","Sales to Date":"2Ω434","Sales Reporting Date":"03/20/2016"},{"Program":"First Spouse","Program Item":"JQ8","Product":"2015 FS GOLD UNC 1/2 OZ - JOHNSON","Sales to Date":"1Ω581","Sales Reporting Date":"03/20/2016"},{"Program":"Special Collectibles","Program Item":"JP8","Product":"2015 PRES $1 & FS MDL SET - JOHNSON","Sales to Date":"6Ω727","Sales Reporting Date":"03/20/2016"},{"Program":"Special Collectibles","Program Item":"P56","Product":"2015 PRES $1 COIN COVER - JOHNSON","Sales to Date":"12Ω200","Sales Reporting Date":"03/20/2016"},{"Program":"Rolls & Bags & Boxes","Program Item":"BZ1","Product":"2015 ATB QTR 100-COIN BAG - BOMBAY (P)","Sales to Date":"2Ω161","Sales Reporting Date":"03/20/2016"},{"Program":"Rolls & Bags & Boxes","Program Item":"BZ2","Product":"2015 ATB QTR 100-COIN BAG - BOMBAY (D)","Sales to Date":"2Ω162","Sales Reporting Date":"03/20/2016"},{"Program":"Rolls & Bags & Boxes","Program Item":"BZ3","Product":"2015 ATB QTR 100-COIN BAG - BOMBAY (S)","Sales to Date":"4Ω327","Sales Reporting Date":"03/20/2016"},{"Program":"Rolls & Bags & Boxes","Program Item":"BZ4","Product":"2015 ATB QTR 2-ROLL SET - BOMBAY (P&D)","Sales to Date":"7Ω530","Sales Reporting Date":"03/20/2016"},{"Program":"Rolls & Bags & Boxes","Program Item":"BZ5","Product":"2015 ATB QTR 40-COIN ROLL - BOMBAY (S)","Sales to Date":"4Ω126","Sales Reporting Date":"03/20/2016"},{"Program":"Rolls & Bags & Boxes","Program Item":"BZ6","Product":"2015 ATB QTR 3-ROLL SET - BOMBAY (P&D&S)","Sales to Date":"9Ω100","Sales Reporting Date":"03/20/2016"},{"Program":"Special Collectibles","Program Item":"NF8","Product":"2015 ATB QTR 3-COIN SET - BOMBAY","Sales to Date":"12Ω496","Sales Reporting Date":"03/20/2016"},{"Program":"Precious Metal Products","Program Item":"SN4","Product":"2015 ATB SILVER UNC 5 OZ - BOMBAY","Sales to Date":"17Ω309","Sales Reporting Date":"03/20/2016"},{"Program":"Annual Sets","Program Item":"DE1","Product":"2015 PRES $1 CIRC SET (P)","Sales to Date":"10Ω210","Sales Reporting Date":"03/20/2016"},{"Program":"Annual Sets","Program Item":"DE2","Product":"2015 PRES $1 CIRC SET (D)","Sales to Date":"8Ω868","Sales Reporting Date":"03/20/2016"},{"Program":"Annual Sets","Program Item":"NE1","Product":"2015 ATB QTR CIRC SET","Sales to Date":"18Ω214","Sales Reporting Date":"03/20/2016"},{"Program":"Special Collectibles","Program Item":"NF9","Product":"2015 ATB QTR 3-COIN SET - SARATG","Sales to Date":"13Ω666","Sales Reporting Date":"03/20/2016"},{"Program":"Precious Metal Products","Program Item":"SN5","Product":"2015 ATB SILVER UNC 5 OZ - SARATG","Sales to Date":"17Ω563","Sales Reporting Date":"03/20/2016"},{"Program":"Rolls & Bags & Boxes","Program Item":"ST1","Product":"2015 ATB QTR 100-COIN BAG - SARATG (P)","Sales to Date":"2Ω184","Sales Reporting Date":"03/20/2016"},{"Program":"Rolls & Bags & Boxes","Program Item":"ST2","Product":"2015 ATB QTR 100-COIN BAG - SARATG (D)","Sales to Date":"2Ω129","Sales Reporting Date":"03/20/2016"},{"Program":"Rolls & Bags & Boxes","Program Item":"ST3","Product":"2015 ATB QTR 100-COIN BAG - SARATG (S)","Sales to Date":"4Ω438","Sales Reporting Date":"03/20/2016"},{"Program":"Rolls & Bags & Boxes","Program Item":"ST4","Product":"2015 ATB QTR 2-ROLL SET - SARATG (P&D)","Sales to Date":"7Ω363","Sales Reporting Date":"03/20/2016"},{"Program":"Rolls & Bags & Boxes","Program Item":"ST5","Product":"2015 ATB QTR 40-COIN ROLL - SARATG (S)","Sales to Date":"4Ω136","Sales Reporting Date":"03/20/2016"},{"Program":"Rolls & Bags & Boxes","Program Item":"ST6","Product":"2015 ATB QTR 3-ROLL SET - SARATG (P&D&S)","Sales to Date":"9Ω039","Sales Reporting Date":"03/20/2016"},{"Program":"Special Collectibles","Program Item":"16RD","Product":"2016 BIRTH SET","Sales to Date":"8Ω764","Sales Reporting Date":"03/20/2016"},{"Program":"Special Collectibles","Program Item":"16RE","Product":"2016 HAPPY BIRTHDAY SET","Sales to Date":"6Ω862","Sales Reporting Date":"03/20/2016"},{"Program":"Commemoratives","Program Item":"16CH","Product":"2016 MARK TWAIN GOLD PROOF","Sales to Date":"10Ω957","Sales Reporting Date":"03/20/2016"},{"Program":"Commemoratives","Program Item":"16CJ","Product":"2016 MARK TWAIN GOLD UNC","Sales to Date":"4Ω848","Sales Reporting Date":"03/20/2016"},{"Program":"Rolls & Bags & Boxes","Program Item":"16NA","Product":"2016 NA $1 25-COIN ROLL (P)","Sales to Date":"12Ω204","Sales Reporting Date":"03/20/2016"},{"Program":"Rolls & Bags & Boxes","Program Item":"16NB","Product":"2016 NA $1 100-COIN BAG (D)","Sales to Date":"12Ω061","Sales Reporting Date":"03/20/2016"},{"Program":"Rolls & Bags & Boxes","Program Item":"16NC","Product":"2016 NA $1 250-COIN BOX (P)","Sales to Date":"1Ω124","Sales Reporting Date":"03/20/2016"},{"Program":"Rolls & Bags & Boxes","Program Item":"16ND","Product":"2016 NA $1 250-COIN BOX (D)","Sales to Date":"1Ω112","Sales Reporting Date":"03/20/2016"},{"Program":"Rolls & Bags & Boxes","Program Item":"16NE","Product":"2016 NA $1 100-COIN BAG (P)","Sales to Date":"652","Sales Reporting Date":"03/20/2016"},{"Program":"Rolls & Bags & Boxes","Program Item":"16NF","Product":"2016 NA $1 25-COIN ROLL (D)","Sales to Date":"727","Sales Reporting Date":"03/20/2016"},{"Program":"Rolls & Bags & Boxes","Program Item":"16ABA","Product":"2016 ATB QTR 100-COIN BAG - SHAWNEE (P)","Sales to Date":"1Ω915","Sales Reporting Date":"03/20/2016"},{"Program":"Rolls & Bags & Boxes","Program Item":"16ABB","Product":"2016 ATB QTR 100-COIN BAG - SHAWNEE (D)","Sales to Date":"1Ω894","Sales Reporting Date":"03/20/2016"},{"Program":"Rolls & Bags & Boxes","Program Item":"16ABC","Product":"2016 ATB QTR 100-COIN BAG - SHAWNEE (S)","Sales to Date":"3Ω525","Sales Reporting Date":"03/20/2016"},{"Program":"Rolls & Bags & Boxes","Program Item":"16ARA","Product":"2016 ATB QTR 2-ROLL SET - SHAWNEE (P&D)","Sales to Date":"6Ω934","Sales Reporting Date":"03/20/2016"},{"Program":"Rolls & Bags & Boxes","Program Item":"16ARB","Product":"2016 ATB QTR 40-COIN ROLL - SHAWNEE (S)","Sales to Date":"3Ω355","Sales Reporting Date":"03/20/2016"},{"Program":"Rolls & Bags & Boxes","Program Item":"16ARC","Product":"2016 ATB QTR 3-ROLL SET - SHAWNEE (P&D&S)","Sales to Date":"8Ω107","Sales Reporting Date":"03/20/2016"},{"Program":"Commemoratives","Program Item":"16CK","Product":"2016 MARK TWAIN SILVER PROOF","Sales to Date":"52Ω922","Sales Reporting Date":"03/20/2016"},{"Program":"Commemoratives","Program Item":"16CL","Product":"2016 MARK TWAIN SILVER UNC","Sales to Date":"19Ω991","Sales Reporting Date":"03/20/2016"},{"Program":"Rolls & Bags & Boxes","Program Item":"16PG","Product":"2016 PRES $1 25-COIN ROLL - NIXON (P)","Sales to Date":"36Ω667","Sales Reporting Date":"03/20/2016"},{"Program":"Rolls & Bags & Boxes","Program Item":"16PH","Product":"2016 PRES $1 25-COIN ROLL - NIXON (D)","Sales to Date":"32Ω081","Sales Reporting Date":"03/20/2016"},{"Program":"Rolls & Bags & Boxes","Program Item":"16PJ","Product":"2016 PRES $1 250-COIN BOX - NIXON (P)","Sales to Date":"3Ω587","Sales Reporting Date":"03/20/2016"},{"Program":"Rolls & Bags & Boxes","Program Item":"16PK","Product":"2016 PRES $1 250-COIN BOX - NIXON (D)","Sales to Date":"3Ω328","Sales Reporting Date":"03/20/2016"},{"Program":"Rolls & Bags & Boxes","Program Item":"16PL","Product":"2016 PRES $1 100-COIN BAG - NIXON (P)","Sales to Date":"928","Sales Reporting Date":"03/20/2016"},{"Program":"Rolls & Bags & Boxes","Program Item":"16PM","Product":"2016 PRES $1 100-COIN BAG - NIXON (D)","Sales to Date":"911","Sales Reporting Date":"03/20/2016"},{"Program":"Annual Sets","Program Item":"16P3","Product":"2016 PRES $1 PROOF SET","Sales to Date":"134Ω160","Sales Reporting Date":"03/20/2016"},{"Program":"First Spouse","Program Item":"16SA","Product":"2016 FS GOLD PROOF 1/2 OZ - NIXON","Sales to Date":"1Ω826","Sales Reporting Date":"03/20/2016"},{"Program":"First Spouse","Program Item":"16SB","Product":"2016 FS GOLD UNC 1/2 OZ - NIXON","Sales to Date":"1Ω052","Sales Reporting Date":"03/20/2016"},{"Program":"Special Collectibles","Program Item":"16AD","Product":"2016 ATB QTR 3-COIN SET - SHAWNEE","Sales to Date":"10Ω571","Sales Reporting Date":"03/20/2016"},{"Program":"Annual Sets","Program Item":"16AP","Product":"2016 ATB QTR PROOF SET","Sales to Date":"46Ω579","Sales Reporting Date":"03/20/2016"},{"Program":"Rolls & Bags & Boxes","Program Item":"16KA","Product":"2016 HALF-DOLLAR 200-COIN BAG (P&D)","Sales to Date":"4Ω181","Sales Reporting Date":"03/20/2016"},{"Program":"Rolls & Bags & Boxes","Program Item":"16KB","Product":"2016 HALF-DOLLAR 2-ROLL SET (P&D)","Sales to Date":"13Ω882","Sales Reporting Date":"03/20/2016"},{"Program":"Precious Metal Products","Program Item":"16AJ","Product":"2016 ATB SILVER UNC 5 OZ - SHAWNEE","Sales to Date":"16Ω402","Sales Reporting Date":"03/20/2016"},{"Program":"Special Collectibles","Program Item":"16FA","Product":"2016 PRES $1 COIN COVER - NIXON","Sales to Date":"11Ω815","Sales Reporting Date":"03/20/2016"},{"Program":"Special Collectibles","Program Item":"16PD","Product":"2016 PRES $1 & FS MDL SET - NIXON","Sales to Date":"3Ω325","Sales Reporting Date":"03/20/2016"},{"Program":"Annual Sets","Program Item":"16AQ","Product":"2016 ATB QTR SILVER PROOF SET","Sales to Date":"56Ω342","Sales Reporting Date":"03/20/2016"},{"Program":"Rolls & Bags & Boxes","Program Item":"16PN","Product":"2016 PRES $1 25-COIN ROLL - FORD (P)","Sales to Date":"31Ω132","Sales Reporting Date":"03/20/2016"},{"Program":"Rolls & Bags & Boxes","Program Item":"16PP","Product":"2016 PRES $1 25-COIN ROLL - FORD (D)","Sales to Date":"29Ω258","Sales Reporting Date":"03/20/2016"},{"Program":"Rolls & Bags & Boxes","Program Item":"16PQ","Product":"2016 PRES $1 250-COIN BOX - FORD (P)","Sales to Date":"2Ω756","Sales Reporting Date":"03/20/2016"},{"Program":"Rolls & Bags & Boxes","Program Item":"16PR","Product":"2016 PRES $1 250-COIN BOX - FORD (D)","Sales to Date":"2Ω436","Sales Reporting Date":"03/20/2016"},{"Program":"Rolls & Bags & Boxes","Program Item":"16PS","Product":"2016 PRES $1 100-COIN BAG - FORD (P)","Sales to Date":"786","Sales Reporting Date":"03/20/2016"},{"Program":"Rolls & Bags & Boxes","Program Item":"16PT","Product":"2016 PRES $1 100-COIN BAG - FORD (D)","Sales to Date":"724","Sales Reporting Date":"03/20/2016"},{"Program":"Precious Metal Products","Program Item":"16EB","Product":"2016 AM EAGLE GOLD PROOF 1 OZ","Sales to Date":"6Ω573","Sales Reporting Date":"03/20/2016"},{"Program":"Precious Metal Products","Program Item":"16EC","Product":"2016 AM EAGLE GOLD PROOF 1/2 OZ","Sales to Date":"1Ω969","Sales Reporting Date":"03/20/2016"},{"Program":"Precious Metal Products","Program Item":"16ED","Product":"2016 AM EAGLE GOLD PROOF 1/4 OZ","Sales to Date":"2Ω143","Sales Reporting Date":"03/20/2016"},{"Program":"Precious Metal Products","Program Item":"16EE","Product":"2016 AM EAGLE GOLD PROOF 1/10 OZ","Sales to Date":"8Ω036","Sales Reporting Date":"03/20/2016"},{"Program":"Precious Metal Products","Program Item":"16EF","Product":"2016 AM EAGLE GOLD PROOF 4-COIN SET","Sales to Date":"6Ω738","Sales Reporting Date":"03/20/2016"}]